opentelemetry/distro/__init__.py
opentelemetry/distro/py.typed
opentelemetry/distro/version.py
opentelemetry_distro-0.58b0.dist-info/METADATA
opentelemetry_distro-0.58b0.dist-info/WHEEL
opentelemetry_distro-0.58b0.dist-info/entry_points.txt
opentelemetry_distro-0.58b0.dist-info/RECORD
